LICENSE
pytest_asteroid/__init__.py
pytest_asteroid/asteroid.py
pytest_asteroid-0.4.1.dist-info/entry_points.txt
pytest_asteroid-0.4.1.dist-info/LICENSE
pytest_asteroid-0.4.1.dist-info/WHEEL
pytest_asteroid-0.4.1.dist-info/METADATA
pytest_asteroid-0.4.1.dist-info/RECORD
