Metadata-Version: 2.1
Name: pytest-asteroid
Version: 0.4.1
Summary: PyTest plugin for docker-based testing on database images
Home-page: https://github.com/stabtazer/pytest-asteroid
License: Apache-2.0
Keywords: pytest,testing,docker,compose,database,mysql
Author: Emil Buus Sauer-Strømberg
Author-email: emil.sauer@gmail.com
Requires-Python: >=3.7,<4.0
Classifier: Framework :: Pytest
Classifier: License :: OSI Approved :: Apache Software License
Classifier: Programming Language :: Python :: 3
Classifier: Programming Language :: Python :: 3.10
Classifier: Programming Language :: Python :: 3.7
Classifier: Programming Language :: Python :: 3.8
Classifier: Programming Language :: Python :: 3.9
Requires-Dist: PyMySQL (>=1.0.2,<2.0.0)
Requires-Dist: docker-compose (>=1.29.2,<2.0.0)
Requires-Dist: lovely-pytest-docker (==0.3.0)
Requires-Dist: poetry (>=1.0,<2.0)
Requires-Dist: pytest (>=6.2.5,<8.0.0)
Project-URL: Repository, https://github.com/stabtazer/pytest-asteroid
